poetry_fastapi_demo/__init__.py
poetry_fastapi_demo/main.py
poetry_fastapi_demo/models/__init__.py
poetry_fastapi_demo/models/user.py
poetry_fastapi_demo/routers/__init__.py
poetry_fastapi_demo/routers/user.py
poetry_fastapi_demo/tables/__init__.py
poetry_fastapi_demo/tables/user.py
poetry_fastapi_demo-0.0.1.dist-info/LICENSE
poetry_fastapi_demo-0.0.1.dist-info/METADATA
poetry_fastapi_demo-0.0.1.dist-info/WHEEL
poetry_fastapi_demo-0.0.1.dist-info/RECORD
